CHANGES.rst
MANIFEST.in
README.rst
setup.cfg
setup.py
tox.ini
version.txt
src/metapensiero.odt2sphinx.egg-info/PKG-INFO
src/metapensiero.odt2sphinx.egg-info/SOURCES.txt
src/metapensiero.odt2sphinx.egg-info/dependency_links.txt
src/metapensiero.odt2sphinx.egg-info/entry_points.txt
src/metapensiero.odt2sphinx.egg-info/namespace_packages.txt
src/metapensiero.odt2sphinx.egg-info/requires.txt
src/metapensiero.odt2sphinx.egg-info/top_level.txt
src/metapensiero/odt2sphinx/__init__.py
src/metapensiero/odt2sphinx/__main__.py
src/metapensiero/odt2sphinx/odt.py
src/metapensiero/odt2sphinx/out.py
src/metapensiero/odt2sphinx/rst.py
src/metapensiero/odt2sphinx/table.py
src/metapensiero/odt2sphinx/visitor.py