Metadata-Version: 1.1
Name: metapensiero.odt2sphinx
Version: 2.7
Summary: An OpenDocument to reStructuredText/Sphinx converter.
Home-page: https://bitbucket.org/lele/metapensiero.odt2sphinx
Author: Lele Gaifax
Author-email: lele@metapensiero.it
License: PSF License
Platform: UNKNOWN
Classifier: Development Status :: 4 - Beta
Classifier: Environment :: Console
Classifier: License :: OSI Approved :: Python Software Foundation License
Classifier: Programming Language :: Python :: 3
Classifier: Programming Language :: Python :: 3.4
Classifier: Programming Language :: Python :: 3.5
Classifier: Topic :: Documentation
Classifier: Topic :: Text Processing
